cache_fallback/__init__.py
cache_fallback/cache.py
tests/testapp/__init__.py
django_cache_fallback-0.2.2.dist-info/AUTHORS
django_cache_fallback-0.2.2.dist-info/LICENSE
django_cache_fallback-0.2.2.dist-info/METADATA
django_cache_fallback-0.2.2.dist-info/WHEEL
django_cache_fallback-0.2.2.dist-info/top_level.txt
django_cache_fallback-0.2.2.dist-info/RECORD
