Metadata-Version: 2.1
Name: django-cache-fallback
Version: 0.2.2
Summary: Django Cache Fallback
Home-page: https://github.com/Kub-AT/django-cache-fallback
Author: Jakub Stawowy
Author-email: Kub-AT@users.noreply.github.com
License: 3-clause BSD
Keywords: django-cache-fallback,django cache,multiple cache,fallback cache
Platform: any
Classifier: Programming Language :: Python
Classifier: Programming Language :: Python :: 2
Classifier: Programming Language :: Python :: 2.7
Classifier: Programming Language :: Python :: 3
Classifier: Programming Language :: Python :: 3.4
Classifier: Programming Language :: Python :: 3.5
Classifier: Programming Language :: Python :: 3.6
Classifier: Programming Language :: Python :: 3.7
Classifier: Development Status :: 5 - Production/Stable
Classifier: Environment :: Web Environment
Classifier: Framework :: Django
Classifier: Framework :: Django :: 2.2
Classifier: Framework :: Django :: 2.1
Classifier: Framework :: Django :: 2.0
Classifier: Framework :: Django :: 1.11
Classifier: Framework :: Django :: 1.10
Classifier: Framework :: Django :: 1.9
Classifier: Framework :: Django :: 1.8
Classifier: Intended Audience :: Developers
Requires-Dist: django (>=1.8)
